<atlassian-plugin key="${project.groupId}.${project.artifactId}" name="${project.name}" plugins-version="2">
  <plugin-info>
    <description>${project.description}</description>
    <version>${project.version}</version>
    <vendor name="${project.organization.name}" url="${project.organization.url}" />
    <param name="configure.url">/secure/admin/configureRevikiPlugin.jspa</param>
  </plugin-info>

  <component-import key="pluginSettingsFactory"
                    interface="com.atlassian.sal.api.pluginsettings.PluginSettingsFactory" />

  <jira-renderer key="atlassian-jira-reviki-renderer"
                 name="Reviki Renderer"
                 class="net.hillsdon.reviki.jira.renderer.JiraRevikiRenderingPlugin">
    <description>A field renderer that will render Reviki content</description>
    <resource type="velocity" name="edit" location="templates/reviki-edit.vm"/>
  </jira-renderer>

  <web-resource key="atlassian-jira-reviki-css" name="Jira Reviki Renderer CSS">
    <context>jira.general</context>
    <resource type="download" name="reviki-style.css" location="style/reviki-style.css"/>
  </web-resource>

  <webwork1 key="atlassian-jira-reviki-config"
            name="Jira Reviki Renderer Configuration"
            class="java.lang.Object">
    <actions>
      <action name="net.hillsdon.reviki.jira.renderer.WebConfig"
              alias="configureRevikiPlugin"
              roles-required="sysadmin">
        <view name="input">templates/reviki-config.vm</view>
        <view name="success">templates/reviki-config.vm</view>
      </action>
    </actions>
  </webwork1>
</atlassian-plugin>